{"asseti736e27c09d9746649f08839c16b50381c77c933b":{"objectType":"file","fileUrl":null,"mimeType":null,"attachments":null,"author":null,"content":"I need a guide: matt wisniewski","displayName":null,"downstreamDuplicates":null,"id":"asseti736e27c09d9746649f08839c16b50381c77c933b","image":{"duration":null,"height":480,"url":"http:\/\/img.ffffound.com\/static-data\/assets\/6\/736e27c09d9746649f08839c16b50381c77c933b_m.jpg","width":360},"published":null,"summary":null,"updated":null,"upstreamDuplicates":null,"url":"http:\/\/ineedaguide.blogspot.it\/2012\/04\/matt-wisniewski.html","@download":"\/api\/ffffound\/download?url=http:\/\/img.ffffound.com\/static-data\/assets\/6\/736e27c09d9746649f08839c16b50381c77c933b_m.jpg","@fffoundUrl":"http:\/\/ffffound.com\/image\/736e27c09d9746649f08839c16b50381c77c933b"},"asseti58c8dd9a5883be03c4c51948ca731c8989dbe98d":{"objectType":"file","fileUrl":null,"mimeType":null,"attachments":null,"author":null,"content":"Steve Hockett | Arcademi","displayName":null,"downstreamDuplicates":null,"id":"asseti58c8dd9a5883be03c4c51948ca731c8989dbe98d","image":{"duration":null,"height":480,"url":"http:\/\/img.ffffound.com\/static-data\/assets\/6\/58c8dd9a5883be03c4c51948ca731c8989dbe98d_m.jpg","width":360},"published":null,"summary":null,"updated":null,"upstreamDuplicates":null,"url":"http:\/\/www.arcademi.com\/steve-hockett\/","@download":"\/api\/ffffound\/download?url=http:\/\/img.ffffound.com\/static-data\/assets\/6\/58c8dd9a5883be03c4c51948ca731c8989dbe98d_m.jpg","@fffoundUrl":"http:\/\/ffffound.com\/image\/58c8dd9a5883be03c4c51948ca731c8989dbe98d"},"asseti960aa2183e596b413d37c8412bcfc551c5dbd18b":{"objectType":"file","fileUrl":null,"mimeType":null,"attachments":null,"author":null,"content":"Tumblr","displayName":null,"downstreamDuplicates":null,"id":"asseti960aa2183e596b413d37c8412bcfc551c5dbd18b","image":{"duration":null,"height":480,"url":"http:\/\/img.ffffound.com\/static-data\/assets\/6\/960aa2183e596b413d37c8412bcfc551c5dbd18b_m.jpg","width":320},"published":null,"summary":null,"updated":null,"upstreamDuplicates":null,"url":"http:\/\/www.tumblr.com\/dashboard\/10\/8099573109","@download":"\/api\/ffffound\/download?url=http:\/\/img.ffffound.com\/static-data\/assets\/6\/960aa2183e596b413d37c8412bcfc551c5dbd18b_m.jpg","@fffoundUrl":"http:\/\/ffffound.com\/image\/960aa2183e596b413d37c8412bcfc551c5dbd18b"},"assetia69140cc56c4381d2e44e15b446e9d45d0b6c201":{"objectType":"file","fileUrl":null,"mimeType":null,"attachments":null,"author":null,"content":"Color Berlin 2 on the Behance Network","displayName":null,"downstreamDuplicates":null,"id":"assetia69140cc56c4381d2e44e15b446e9d45d0b6c201","image":{"duration":null,"height":480,"url":"http:\/\/img.ffffound.com\/static-data\/assets\/6\/a69140cc56c4381d2e44e15b446e9d45d0b6c201_m.jpg","width":480},"published":null,"summary":null,"updated":null,"upstreamDuplicates":null,"url":"http:\/\/www.behance.net\/Gallery\/Color-Berlin-2\/513463","@download":"\/api\/ffffound\/download?url=http:\/\/img.ffffound.com\/static-data\/assets\/6\/a69140cc56c4381d2e44e15b446e9d45d0b6c201_m.jpg","@fffoundUrl":"http:\/\/ffffound.com\/image\/a69140cc56c4381d2e44e15b446e9d45d0b6c201"},"asseti1339979dfcb6f5d60dd670360c22152465c08048":{"objectType":"file","fileUrl":null,"mimeType":null,"attachments":null,"author":null,"content":"automatism","displayName":null,"downstreamDuplicates":null,"id":"asseti1339979dfcb6f5d60dd670360c22152465c08048","image":{"duration":null,"height":400,"url":"http:\/\/img.ffffound.com\/static-data\/assets\/6\/1339979dfcb6f5d60dd670360c22152465c08048_m.jpg","width":266},"published":null,"summary":null,"updated":null,"upstreamDuplicates":null,"url":"http:\/\/lorilangille.blogspot.com\/search?updated-max=2008-11-13T00%3A01%3A00-05%3A00&max-results=20","@download":"\/api\/ffffound\/download?url=http:\/\/img.ffffound.com\/static-data\/assets\/6\/1339979dfcb6f5d60dd670360c22152465c08048_m.jpg","@fffoundUrl":"http:\/\/ffffound.com\/image\/1339979dfcb6f5d60dd670360c22152465c08048"},"asseti34873d63695d15a1e5609ef6d7ddabc27e1c919d":{"objectType":"file","fileUrl":null,"mimeType":null,"attachments":null,"author":null,"content":"THEM THANGS","displayName":null,"downstreamDuplicates":null,"id":"asseti34873d63695d15a1e5609ef6d7ddabc27e1c919d","image":{"duration":null,"height":480,"url":"http:\/\/img.ffffound.com\/static-data\/assets\/6\/34873d63695d15a1e5609ef6d7ddabc27e1c919d_m.jpg","width":291},"published":null,"summary":null,"updated":null,"upstreamDuplicates":null,"url":"http:\/\/jblyth.com\/blog_02.html","@download":"\/api\/ffffound\/download?url=http:\/\/img.ffffound.com\/static-data\/assets\/6\/34873d63695d15a1e5609ef6d7ddabc27e1c919d_m.jpg","@fffoundUrl":"http:\/\/ffffound.com\/image\/34873d63695d15a1e5609ef6d7ddabc27e1c919d"},"assetidd5c81aeb5b1c3b27602cc6b6634b041126d82b6":{"objectType":"file","fileUrl":null,"mimeType":null,"attachments":null,"author":null,"content":"(1) Tumblr","displayName":null,"downstreamDuplicates":null,"id":"assetidd5c81aeb5b1c3b27602cc6b6634b041126d82b6","image":{"duration":null,"height":323,"url":"http:\/\/img.ffffound.com\/static-data\/assets\/6\/dd5c81aeb5b1c3b27602cc6b6634b041126d82b6_m.jpg","width":480},"published":null,"summary":null,"updated":null,"upstreamDuplicates":null,"url":"http:\/\/www.tumblr.com\/dashboard","@download":"\/api\/ffffound\/download?url=http:\/\/img.ffffound.com\/static-data\/assets\/6\/dd5c81aeb5b1c3b27602cc6b6634b041126d82b6_m.jpg","@fffoundUrl":"http:\/\/ffffound.com\/image\/dd5c81aeb5b1c3b27602cc6b6634b041126d82b6"},"asseti32d52f17847a99dd1c3cc9b42b8f12316e8502d1":{"objectType":"file","fileUrl":null,"mimeType":null,"attachments":null,"author":null,"content":"17.jpg 790\u00d7426 pixels","displayName":null,"downstreamDuplicates":null,"id":"asseti32d52f17847a99dd1c3cc9b42b8f12316e8502d1","image":{"duration":null,"height":259,"url":"http:\/\/img.ffffound.com\/static-data\/assets\/6\/32d52f17847a99dd1c3cc9b42b8f12316e8502d1_m.jpg","width":480},"published":null,"summary":null,"updated":null,"upstreamDuplicates":null,"url":"http:\/\/www.montecitopavilion.com\/img\/home\/large\/17.jpg","@download":"\/api\/ffffound\/download?url=http:\/\/img.ffffound.com\/static-data\/assets\/6\/32d52f17847a99dd1c3cc9b42b8f12316e8502d1_m.jpg","@fffoundUrl":"http:\/\/ffffound.com\/image\/32d52f17847a99dd1c3cc9b42b8f12316e8502d1"},"asseti9101bd5b48dfbdf8380addfcd87bb77e4f94dd01":{"objectType":"file","fileUrl":null,"mimeType":null,"attachments":null,"author":null,"content":"Strange Worlds on the Behance Network","displayName":null,"downstreamDuplicates":null,"id":"asseti9101bd5b48dfbdf8380addfcd87bb77e4f94dd01","image":{"duration":null,"height":480,"url":"http:\/\/img.ffffound.com\/static-data\/assets\/6\/9101bd5b48dfbdf8380addfcd87bb77e4f94dd01_m.jpg","width":355},"published":null,"summary":null,"updated":null,"upstreamDuplicates":null,"url":"http:\/\/www.behance.net\/MatthewAlbanese\/frame\/366923","@download":"\/api\/ffffound\/download?url=http:\/\/img.ffffound.com\/static-data\/assets\/6\/9101bd5b48dfbdf8380addfcd87bb77e4f94dd01_m.jpg","@fffoundUrl":"http:\/\/ffffound.com\/image\/9101bd5b48dfbdf8380addfcd87bb77e4f94dd01"},"asseti3cf6838b6fe8041c79eaff9bb487d5a5763c4e80":{"objectType":"file","fileUrl":null,"mimeType":null,"attachments":null,"author":null,"content":"Sa\u00efdSeeing","displayName":null,"downstreamDuplicates":null,"id":"asseti3cf6838b6fe8041c79eaff9bb487d5a5763c4e80","image":{"duration":null,"height":377,"url":"http:\/\/img.ffffound.com\/static-data\/assets\/6\/3cf6838b6fe8041c79eaff9bb487d5a5763c4e80_m.jpg","width":480},"published":null,"summary":null,"updated":null,"upstreamDuplicates":null,"url":"http:\/\/saidseeing.tumblr.com\/","@download":"\/api\/ffffound\/download?url=http:\/\/img.ffffound.com\/static-data\/assets\/6\/3cf6838b6fe8041c79eaff9bb487d5a5763c4e80_m.jpg","@fffoundUrl":"http:\/\/ffffound.com\/image\/3cf6838b6fe8041c79eaff9bb487d5a5763c4e80"},"asseti96b58707ed6c6f05bba943a1d0ee1760a649e063":{"objectType":"file","fileUrl":null,"mimeType":null,"attachments":null,"author":null,"content":"Magnificent Ruin","displayName":null,"downstreamDuplicates":null,"id":"asseti96b58707ed6c6f05bba943a1d0ee1760a649e063","image":{"duration":null,"height":318,"url":"http:\/\/img.ffffound.com\/static-data\/assets\/6\/96b58707ed6c6f05bba943a1d0ee1760a649e063_m.jpg","width":480},"published":null,"summary":null,"updated":null,"upstreamDuplicates":null,"url":"http:\/\/www.magnificentruin.com\/","@download":"\/api\/ffffound\/download?url=http:\/\/img.ffffound.com\/static-data\/assets\/6\/96b58707ed6c6f05bba943a1d0ee1760a649e063_m.jpg","@fffoundUrl":"http:\/\/ffffound.com\/image\/96b58707ed6c6f05bba943a1d0ee1760a649e063"},"asseti54ada79649a6548e3eac45da6e649378e11c063a":{"objectType":"file","fileUrl":null,"mimeType":null,"attachments":null,"author":null,"content":"Tumblr","displayName":null,"downstreamDuplicates":null,"id":"asseti54ada79649a6548e3eac45da6e649378e11c063a","image":{"duration":null,"height":480,"url":"http:\/\/img.ffffound.com\/static-data\/assets\/6\/54ada79649a6548e3eac45da6e649378e11c063a_m.jpg","width":320},"published":null,"summary":null,"updated":null,"upstreamDuplicates":null,"url":"http:\/\/www.tumblr.com\/dashboard\/11\/8098581167","@download":"\/api\/ffffound\/download?url=http:\/\/img.ffffound.com\/static-data\/assets\/6\/54ada79649a6548e3eac45da6e649378e11c063a_m.jpg","@fffoundUrl":"http:\/\/ffffound.com\/image\/54ada79649a6548e3eac45da6e649378e11c063a"},"asseti4ad06efa4c0a8a32101b9054749ca760e15712a6":{"objectType":"file","fileUrl":null,"mimeType":null,"attachments":null,"author":null,"content":"Tino Seubert | Arcademi","displayName":null,"downstreamDuplicates":null,"id":"asseti4ad06efa4c0a8a32101b9054749ca760e15712a6","image":{"duration":null,"height":480,"url":"http:\/\/img.ffffound.com\/static-data\/assets\/6\/4ad06efa4c0a8a32101b9054749ca760e15712a6_m.jpg","width":360},"published":null,"summary":null,"updated":null,"upstreamDuplicates":null,"url":"http:\/\/www.arcademi.com\/tino-seubert\/","@download":"\/api\/ffffound\/download?url=http:\/\/img.ffffound.com\/static-data\/assets\/6\/4ad06efa4c0a8a32101b9054749ca760e15712a6_m.jpg","@fffoundUrl":"http:\/\/ffffound.com\/image\/4ad06efa4c0a8a32101b9054749ca760e15712a6"},"asseti63846bd5d7c07b5e26accef24a8f4eef1c2c6ca9":{"objectType":"file","fileUrl":null,"mimeType":null,"attachments":null,"author":null,"content":"Flickr Photo Download: Adderall XR-15mg","displayName":null,"downstreamDuplicates":null,"id":"asseti63846bd5d7c07b5e26accef24a8f4eef1c2c6ca9","image":{"duration":null,"height":480,"url":"http:\/\/img.ffffound.com\/static-data\/assets\/6\/63846bd5d7c07b5e26accef24a8f4eef1c2c6ca9_m.png","width":311},"published":null,"summary":null,"updated":null,"upstreamDuplicates":null,"url":"http:\/\/www.flickr.com\/photos\/adamcrowe\/2331053569\/sizes\/o\/","@download":"\/api\/ffffound\/download?url=http:\/\/img.ffffound.com\/static-data\/assets\/6\/63846bd5d7c07b5e26accef24a8f4eef1c2c6ca9_m.png","@fffoundUrl":"http:\/\/ffffound.com\/image\/63846bd5d7c07b5e26accef24a8f4eef1c2c6ca9"},"assetiedfc37c6af81211a402f8d4c73ee1fa3060e83e9":{"objectType":"file","fileUrl":null,"mimeType":null,"attachments":null,"author":null,"content":"Baubauhaus.","displayName":null,"downstreamDuplicates":null,"id":"assetiedfc37c6af81211a402f8d4c73ee1fa3060e83e9","image":{"duration":null,"height":415,"url":"http:\/\/img.ffffound.com\/static-data\/assets\/6\/edfc37c6af81211a402f8d4c73ee1fa3060e83e9_m.jpg","width":415},"published":null,"summary":null,"updated":null,"upstreamDuplicates":null,"url":"http:\/\/www.baubauhaus.com\/image\/36560","@download":"\/api\/ffffound\/download?url=http:\/\/img.ffffound.com\/static-data\/assets\/6\/edfc37c6af81211a402f8d4c73ee1fa3060e83e9_m.jpg","@fffoundUrl":"http:\/\/ffffound.com\/image\/edfc37c6af81211a402f8d4c73ee1fa3060e83e9"},"assetib83008ec943d42bd3c2da08f39fa366d5a64b449":{"objectType":"file","fileUrl":null,"mimeType":null,"attachments":null,"author":null,"content":"Dropular - Media Bookmarking","displayName":null,"downstreamDuplicates":null,"id":"assetib83008ec943d42bd3c2da08f39fa366d5a64b449","image":{"duration":null,"height":349,"url":"http:\/\/img.ffffound.com\/static-data\/assets\/6\/b83008ec943d42bd3c2da08f39fa366d5a64b449_m.jpg","width":468},"published":null,"summary":null,"updated":null,"upstreamDuplicates":null,"url":"http:\/\/dropular.net\/","@download":"\/api\/ffffound\/download?url=http:\/\/img.ffffound.com\/static-data\/assets\/6\/b83008ec943d42bd3c2da08f39fa366d5a64b449_m.jpg","@fffoundUrl":"http:\/\/ffffound.com\/image\/b83008ec943d42bd3c2da08f39fa366d5a64b449"},"assetiaebd2234ae433c301fb9cbf52e3bf1c7835f41a2":{"objectType":"file","fileUrl":null,"mimeType":null,"attachments":null,"author":null,"content":"The Black Workshop","displayName":null,"downstreamDuplicates":null,"id":"assetiaebd2234ae433c301fb9cbf52e3bf1c7835f41a2","image":{"duration":null,"height":480,"url":"http:\/\/img.ffffound.com\/static-data\/assets\/6\/aebd2234ae433c301fb9cbf52e3bf1c7835f41a2_m.jpg","width":320},"published":null,"summary":null,"updated":null,"upstreamDuplicates":null,"url":"http:\/\/theblackworkshop.tumblr.com\/","@download":"\/api\/ffffound\/download?url=http:\/\/img.ffffound.com\/static-data\/assets\/6\/aebd2234ae433c301fb9cbf52e3bf1c7835f41a2_m.jpg","@fffoundUrl":"http:\/\/ffffound.com\/image\/aebd2234ae433c301fb9cbf52e3bf1c7835f41a2"},"asseti77b0593935496787f0aca9a94ee2f736faff5a9c":{"objectType":"file","fileUrl":null,"mimeType":null,"attachments":null,"author":null,"content":"District Lane Lookbook by Zhang Qingyun | Allan Peters' Blog","displayName":null,"downstreamDuplicates":null,"id":"asseti77b0593935496787f0aca9a94ee2f736faff5a9c","image":{"duration":null,"height":480,"url":"http:\/\/img.ffffound.com\/static-data\/assets\/6\/77b0593935496787f0aca9a94ee2f736faff5a9c_m.jpg","width":360},"published":null,"summary":null,"updated":null,"upstreamDuplicates":null,"url":"http:\/\/allanpeters.com\/blog\/?p=6956","@download":"\/api\/ffffound\/download?url=http:\/\/img.ffffound.com\/static-data\/assets\/6\/77b0593935496787f0aca9a94ee2f736faff5a9c_m.jpg","@fffoundUrl":"http:\/\/ffffound.com\/image\/77b0593935496787f0aca9a94ee2f736faff5a9c"},"assetibccdac8fac5321277e98b9879570453695308a46":{"objectType":"file","fileUrl":null,"mimeType":null,"attachments":null,"author":null,"content":"Tumblr","displayName":null,"downstreamDuplicates":null,"id":"assetibccdac8fac5321277e98b9879570453695308a46","image":{"duration":null,"height":480,"url":"http:\/\/img.ffffound.com\/static-data\/assets\/6\/bccdac8fac5321277e98b9879570453695308a46_m.jpg","width":480},"published":null,"summary":null,"updated":null,"upstreamDuplicates":null,"url":"http:\/\/www.tumblr.com\/dashboard","@download":"\/api\/ffffound\/download?url=http:\/\/img.ffffound.com\/static-data\/assets\/6\/bccdac8fac5321277e98b9879570453695308a46_m.jpg","@fffoundUrl":"http:\/\/ffffound.com\/image\/bccdac8fac5321277e98b9879570453695308a46"},"asseti3ec6431f863c8bcff5c7a8d2b325ad901e9ce97e":{"objectType":"file","fileUrl":null,"mimeType":null,"attachments":null,"author":null,"content":"2185311349_680125d120.jpg (JPEG Image, 368x500 pixels)","displayName":null,"downstreamDuplicates":null,"id":"asseti3ec6431f863c8bcff5c7a8d2b325ad901e9ce97e","image":{"duration":null,"height":480,"url":"http:\/\/img.ffffound.com\/static-data\/assets\/6\/3ec6431f863c8bcff5c7a8d2b325ad901e9ce97e_m.jpg","width":353},"published":null,"summary":null,"updated":null,"upstreamDuplicates":null,"url":"http:\/\/illustrationfriday.com\/blog\/page\/12\/","@download":"\/api\/ffffound\/download?url=http:\/\/img.ffffound.com\/static-data\/assets\/6\/3ec6431f863c8bcff5c7a8d2b325ad901e9ce97e_m.jpg","@fffoundUrl":"http:\/\/ffffound.com\/image\/3ec6431f863c8bcff5c7a8d2b325ad901e9ce97e"},"asseti853ebb0b1dd84e4748aa3c45e152c0d3f7240417":{"objectType":"file","fileUrl":null,"mimeType":null,"attachments":null,"author":null,"content":"Drop Anchors","displayName":null,"downstreamDuplicates":null,"id":"asseti853ebb0b1dd84e4748aa3c45e152c0d3f7240417","image":{"duration":null,"height":480,"url":"http:\/\/img.ffffound.com\/static-data\/assets\/6\/853ebb0b1dd84e4748aa3c45e152c0d3f7240417_m.jpg","width":319},"published":null,"summary":null,"updated":null,"upstreamDuplicates":null,"url":"http:\/\/dropanchors.tumblr.com\/","@download":"\/api\/ffffound\/download?url=http:\/\/img.ffffound.com\/static-data\/assets\/6\/853ebb0b1dd84e4748aa3c45e152c0d3f7240417_m.jpg","@fffoundUrl":"http:\/\/ffffound.com\/image\/853ebb0b1dd84e4748aa3c45e152c0d3f7240417"},"asseti1211e1c3eb4494fa4bfa7ce49d4cc1e647d9e52d":{"objectType":"file","fileUrl":null,"mimeType":null,"attachments":null,"author":null,"content":"Only where the state ends, there begins the human being who is not... - but does it float","displayName":null,"downstreamDuplicates":null,"id":"asseti1211e1c3eb4494fa4bfa7ce49d4cc1e647d9e52d","image":{"duration":null,"height":323,"url":"http:\/\/img.ffffound.com\/static-data\/assets\/6\/1211e1c3eb4494fa4bfa7ce49d4cc1e647d9e52d_m.jpg","width":480},"published":null,"summary":null,"updated":null,"upstreamDuplicates":null,"url":"http:\/\/butdoesitfloat.com\/Only-where-the-state-ends-there-begins-the-human-being-who-is-not","@download":"\/api\/ffffound\/download?url=http:\/\/img.ffffound.com\/static-data\/assets\/6\/1211e1c3eb4494fa4bfa7ce49d4cc1e647d9e52d_m.jpg","@fffoundUrl":"http:\/\/ffffound.com\/image\/1211e1c3eb4494fa4bfa7ce49d4cc1e647d9e52d"},"asseti054cc2eee2d7800b38b2391f77c93f916c081ce1":{"objectType":"file","fileUrl":null,"mimeType":null,"attachments":null,"author":null,"content":"Every reform movement has a lunatic fringe","displayName":null,"downstreamDuplicates":null,"id":"asseti054cc2eee2d7800b38b2391f77c93f916c081ce1","image":{"duration":null,"height":480,"url":"http:\/\/img.ffffound.com\/static-data\/assets\/6\/054cc2eee2d7800b38b2391f77c93f916c081ce1_m.jpg","width":319},"published":null,"summary":null,"updated":null,"upstreamDuplicates":null,"url":"http:\/\/reform.lt\/","@download":"\/api\/ffffound\/download?url=http:\/\/img.ffffound.com\/static-data\/assets\/6\/054cc2eee2d7800b38b2391f77c93f916c081ce1_m.jpg","@fffoundUrl":"http:\/\/ffffound.com\/image\/054cc2eee2d7800b38b2391f77c93f916c081ce1"},"asseti71e3f9d237d0b56cd290cd097e59bb130d4dc5d0":{"objectType":"file","fileUrl":null,"mimeType":null,"attachments":null,"author":null,"content":"Mike McQuade | Allan Peters' Blog","displayName":null,"downstreamDuplicates":null,"id":"asseti71e3f9d237d0b56cd290cd097e59bb130d4dc5d0","image":{"duration":null,"height":243,"url":"http:\/\/img.ffffound.com\/static-data\/assets\/6\/71e3f9d237d0b56cd290cd097e59bb130d4dc5d0_m.png","width":480},"published":null,"summary":null,"updated":null,"upstreamDuplicates":null,"url":"http:\/\/allanpeters.com\/blog\/?p=7816","@download":"\/api\/ffffound\/download?url=http:\/\/img.ffffound.com\/static-data\/assets\/6\/71e3f9d237d0b56cd290cd097e59bb130d4dc5d0_m.png","@fffoundUrl":"http:\/\/ffffound.com\/image\/71e3f9d237d0b56cd290cd097e59bb130d4dc5d0"},"asseti872498cd10b9803ba423cae76ab2bbba1634ff76":{"objectType":"file","fileUrl":null,"mimeType":null,"attachments":null,"author":null,"content":"The Studio of Dan Cassaro","displayName":null,"downstreamDuplicates":null,"id":"asseti872498cd10b9803ba423cae76ab2bbba1634ff76","image":{"duration":null,"height":330,"url":"http:\/\/img.ffffound.com\/static-data\/assets\/6\/872498cd10b9803ba423cae76ab2bbba1634ff76_m.jpg","width":480},"published":null,"summary":null,"updated":null,"upstreamDuplicates":null,"url":"http:\/\/youngjerks.com\/#\/matix\/","@download":"\/api\/ffffound\/download?url=http:\/\/img.ffffound.com\/static-data\/assets\/6\/872498cd10b9803ba423cae76ab2bbba1634ff76_m.jpg","@fffoundUrl":"http:\/\/ffffound.com\/image\/872498cd10b9803ba423cae76ab2bbba1634ff76"}}