{"assetic065ff03dc83247d0573dad2be8ffa804ad6d636":{"objectType":"file","fileUrl":null,"mimeType":null,"attachments":null,"author":null,"content":"One day I want to build a snowman on my own\u2026\u2026 | Flickr - Photo Sharing!","displayName":null,"downstreamDuplicates":null,"id":"assetic065ff03dc83247d0573dad2be8ffa804ad6d636","image":{"duration":null,"height":480,"url":"http:\/\/img.ffffound.com\/static-data\/assets\/6\/c065ff03dc83247d0573dad2be8ffa804ad6d636_m.jpg","width":480},"published":null,"summary":null,"updated":null,"upstreamDuplicates":null,"url":"http:\/\/www.flickr.com\/photos\/lonelypeopleart\/6425588455\/","@download":"\/api\/ffffound\/download?url=http:\/\/img.ffffound.com\/static-data\/assets\/6\/c065ff03dc83247d0573dad2be8ffa804ad6d636_m.jpg","@fffoundUrl":"http:\/\/ffffound.com\/image\/c065ff03dc83247d0573dad2be8ffa804ad6d636"},"asseti541a362c185181f8cfe51c621168ec46129164cb":{"objectType":"file","fileUrl":null,"mimeType":null,"attachments":null,"author":null,"content":"Sci-Fi-O-Rama","displayName":null,"downstreamDuplicates":null,"id":"asseti541a362c185181f8cfe51c621168ec46129164cb","image":{"duration":null,"height":480,"url":"http:\/\/img.ffffound.com\/static-data\/assets\/6\/541a362c185181f8cfe51c621168ec46129164cb_m.jpg","width":311},"published":null,"summary":null,"updated":null,"upstreamDuplicates":null,"url":"http:\/\/www.sci-fi-o-rama.com\/","@download":"\/api\/ffffound\/download?url=http:\/\/img.ffffound.com\/static-data\/assets\/6\/541a362c185181f8cfe51c621168ec46129164cb_m.jpg","@fffoundUrl":"http:\/\/ffffound.com\/image\/541a362c185181f8cfe51c621168ec46129164cb"},"asseti31b16aa490a720e7e9ab3a8e42d21d5687bf2d39":{"objectType":"file","fileUrl":null,"mimeType":null,"attachments":null,"author":null,"content":"The Sartorialist: On the Street....Black + White = Grey","displayName":null,"downstreamDuplicates":null,"id":"asseti31b16aa490a720e7e9ab3a8e42d21d5687bf2d39","image":{"duration":null,"height":480,"url":"http:\/\/img.ffffound.com\/static-data\/assets\/6\/31b16aa490a720e7e9ab3a8e42d21d5687bf2d39_m.jpg","width":320},"published":null,"summary":null,"updated":null,"upstreamDuplicates":null,"url":"http:\/\/thesartorialist.blogspot.com\/2009\/01\/on-streetblack-white-grey.html","@download":"\/api\/ffffound\/download?url=http:\/\/img.ffffound.com\/static-data\/assets\/6\/31b16aa490a720e7e9ab3a8e42d21d5687bf2d39_m.jpg","@fffoundUrl":"http:\/\/ffffound.com\/image\/31b16aa490a720e7e9ab3a8e42d21d5687bf2d39"},"asseti7dbd511506d88ff5f240770a391724456c7ab8ef":{"objectType":"file","fileUrl":null,"mimeType":null,"attachments":null,"author":null,"content":"02.jpg 1268\u00a0\u00d7\u00a01118 pixels","displayName":null,"downstreamDuplicates":null,"id":"asseti7dbd511506d88ff5f240770a391724456c7ab8ef","image":{"duration":null,"height":423,"url":"http:\/\/img.ffffound.com\/static-data\/assets\/6\/7dbd511506d88ff5f240770a391724456c7ab8ef_m.jpg","width":480},"published":null,"summary":null,"updated":null,"upstreamDuplicates":null,"url":"http:\/\/www.fulltable.com\/iso\/rv\/b.htm","@download":"\/api\/ffffound\/download?url=http:\/\/img.ffffound.com\/static-data\/assets\/6\/7dbd511506d88ff5f240770a391724456c7ab8ef_m.jpg","@fffoundUrl":"http:\/\/ffffound.com\/image\/7dbd511506d88ff5f240770a391724456c7ab8ef"},"assetie49b760e6c7e0c70139922cdb0ace24c140a588a":{"objectType":"file","fileUrl":null,"mimeType":null,"attachments":null,"author":null,"content":"027.jpg (JPEG Image, 845x1147 pixels)","displayName":null,"downstreamDuplicates":null,"id":"assetie49b760e6c7e0c70139922cdb0ace24c140a588a","image":{"duration":null,"height":480,"url":"http:\/\/img.ffffound.com\/static-data\/assets\/6\/e49b760e6c7e0c70139922cdb0ace24c140a588a_m.jpg","width":354},"published":null,"summary":null,"updated":null,"upstreamDuplicates":null,"url":"http:\/\/tinymediaempire.com\/","@download":"\/api\/ffffound\/download?url=http:\/\/img.ffffound.com\/static-data\/assets\/6\/e49b760e6c7e0c70139922cdb0ace24c140a588a_m.jpg","@fffoundUrl":"http:\/\/ffffound.com\/image\/e49b760e6c7e0c70139922cdb0ace24c140a588a"},"asseti1d570666d8b69011923e98abc1eae23c21fc9b87":{"objectType":"file","fileUrl":null,"mimeType":null,"attachments":null,"author":null,"content":"tumblr_lvpobqGQvV1qc0cxpo1_500.jpg 500\u00d7669 pixels","displayName":null,"downstreamDuplicates":null,"id":"asseti1d570666d8b69011923e98abc1eae23c21fc9b87","image":{"duration":null,"height":480,"url":"http:\/\/img.ffffound.com\/static-data\/assets\/6\/1d570666d8b69011923e98abc1eae23c21fc9b87_m.jpg","width":359},"published":null,"summary":null,"updated":null,"upstreamDuplicates":null,"url":"http:\/\/24.media.tumblr.com\/tumblr_lvpobqGQvV1qc0cxpo1_500.jpg","@download":"\/api\/ffffound\/download?url=http:\/\/img.ffffound.com\/static-data\/assets\/6\/1d570666d8b69011923e98abc1eae23c21fc9b87_m.jpg","@fffoundUrl":"http:\/\/ffffound.com\/image\/1d570666d8b69011923e98abc1eae23c21fc9b87"},"assetibd9f90b584e822b3d4eca0994c83068d76440e2a":{"objectType":"file","fileUrl":null,"mimeType":null,"attachments":null,"author":null,"content":"W E L L \u203b F E D","displayName":null,"downstreamDuplicates":null,"id":"assetibd9f90b584e822b3d4eca0994c83068d76440e2a","image":{"duration":null,"height":480,"url":"http:\/\/img.ffffound.com\/static-data\/assets\/6\/bd9f90b584e822b3d4eca0994c83068d76440e2a_m.jpg","width":320},"published":null,"summary":null,"updated":null,"upstreamDuplicates":null,"url":"http:\/\/well-fed.tumblr.com\/","@download":"\/api\/ffffound\/download?url=http:\/\/img.ffffound.com\/static-data\/assets\/6\/bd9f90b584e822b3d4eca0994c83068d76440e2a_m.jpg","@fffoundUrl":"http:\/\/ffffound.com\/image\/bd9f90b584e822b3d4eca0994c83068d76440e2a"},"asseti57aa2911b23e2ed6be3cdb52740df15b3fb1d6c1":{"objectType":"file","fileUrl":null,"mimeType":null,"attachments":null,"author":null,"content":"The poet is, etymologically, the maker - but does it float","displayName":null,"downstreamDuplicates":null,"id":"asseti57aa2911b23e2ed6be3cdb52740df15b3fb1d6c1","image":{"duration":null,"height":480,"url":"http:\/\/img.ffffound.com\/static-data\/assets\/6\/57aa2911b23e2ed6be3cdb52740df15b3fb1d6c1_m.jpg","width":363},"published":null,"summary":null,"updated":null,"upstreamDuplicates":null,"url":"http:\/\/butdoesitfloat.com\/2541326\/The-poet-is-etymologically-the-maker","@download":"\/api\/ffffound\/download?url=http:\/\/img.ffffound.com\/static-data\/assets\/6\/57aa2911b23e2ed6be3cdb52740df15b3fb1d6c1_m.jpg","@fffoundUrl":"http:\/\/ffffound.com\/image\/57aa2911b23e2ed6be3cdb52740df15b3fb1d6c1"},"asseti9cbe1a3d68c14134cf6d3eb334f408a1f906a3f2":{"objectType":"file","fileUrl":null,"mimeType":null,"attachments":null,"author":null,"content":"Looks like good Illustrations by Anton Semenov","displayName":null,"downstreamDuplicates":null,"id":"asseti9cbe1a3d68c14134cf6d3eb334f408a1f906a3f2","image":{"duration":null,"height":319,"url":"http:\/\/img.ffffound.com\/static-data\/assets\/6\/9cbe1a3d68c14134cf6d3eb334f408a1f906a3f2_m.jpg","width":480},"published":null,"summary":null,"updated":null,"upstreamDuplicates":null,"url":"http:\/\/lookslikegooddesign.com\/illustration-anton-semenov\/","@download":"\/api\/ffffound\/download?url=http:\/\/img.ffffound.com\/static-data\/assets\/6\/9cbe1a3d68c14134cf6d3eb334f408a1f906a3f2_m.jpg","@fffoundUrl":"http:\/\/ffffound.com\/image\/9cbe1a3d68c14134cf6d3eb334f408a1f906a3f2"},"assetic1fe82a0e8d69d2190a51ffc416c9c33a081d52b":{"objectType":"file","fileUrl":null,"mimeType":null,"attachments":null,"author":null,"content":"mabu \u2014 Art Direction & Design","displayName":null,"downstreamDuplicates":null,"id":"assetic1fe82a0e8d69d2190a51ffc416c9c33a081d52b","image":{"duration":null,"height":480,"url":"http:\/\/img.ffffound.com\/static-data\/assets\/6\/c1fe82a0e8d69d2190a51ffc416c9c33a081d52b_m.jpg","width":339},"published":null,"summary":null,"updated":null,"upstreamDuplicates":null,"url":"http:\/\/work.mabu.dk\/#812560\/Posters","@download":"\/api\/ffffound\/download?url=http:\/\/img.ffffound.com\/static-data\/assets\/6\/c1fe82a0e8d69d2190a51ffc416c9c33a081d52b_m.jpg","@fffoundUrl":"http:\/\/ffffound.com\/image\/c1fe82a0e8d69d2190a51ffc416c9c33a081d52b"},"asseti532a211fff5c87d9b6dea14198d066779e1ac42a":{"objectType":"file","fileUrl":null,"mimeType":null,"attachments":null,"author":null,"content":"Christopher Monro DeLorenzo","displayName":null,"downstreamDuplicates":null,"id":"asseti532a211fff5c87d9b6dea14198d066779e1ac42a","image":{"duration":null,"height":480,"url":"http:\/\/img.ffffound.com\/static-data\/assets\/6\/532a211fff5c87d9b6dea14198d066779e1ac42a_m.gif","width":360},"published":null,"summary":null,"updated":null,"upstreamDuplicates":null,"url":"http:\/\/chrisdelorenzo.com\/#1527775\/O-BROTHER-WHERE-ART-THOU","@download":"\/api\/ffffound\/download?url=http:\/\/img.ffffound.com\/static-data\/assets\/6\/532a211fff5c87d9b6dea14198d066779e1ac42a_m.gif","@fffoundUrl":"http:\/\/ffffound.com\/image\/532a211fff5c87d9b6dea14198d066779e1ac42a"},"assetid5e1b71ae8ab5996728b18da8b4c414ad825bc84":{"objectType":"file","fileUrl":null,"mimeType":null,"attachments":null,"author":null,"content":"Creative Collider","displayName":null,"downstreamDuplicates":null,"id":"assetid5e1b71ae8ab5996728b18da8b4c414ad825bc84","image":{"duration":null,"height":480,"url":"http:\/\/img.ffffound.com\/static-data\/assets\/6\/d5e1b71ae8ab5996728b18da8b4c414ad825bc84_m.jpg","width":349},"published":null,"summary":null,"updated":null,"upstreamDuplicates":null,"url":"http:\/\/creativecollider.tumblr.com\/page\/5","@download":"\/api\/ffffound\/download?url=http:\/\/img.ffffound.com\/static-data\/assets\/6\/d5e1b71ae8ab5996728b18da8b4c414ad825bc84_m.jpg","@fffoundUrl":"http:\/\/ffffound.com\/image\/d5e1b71ae8ab5996728b18da8b4c414ad825bc84"},"assetic41872a4c5e91ad748f242816217ed7a121a6d87":{"objectType":"file","fileUrl":null,"mimeType":null,"attachments":null,"author":null,"content":"tumblr_l8vijrvP0d1qanndio1_500.jpg 500\u00d7368 pixels","displayName":null,"downstreamDuplicates":null,"id":"assetic41872a4c5e91ad748f242816217ed7a121a6d87","image":{"duration":null,"height":353,"url":"http:\/\/img.ffffound.com\/static-data\/assets\/6\/c41872a4c5e91ad748f242816217ed7a121a6d87_m.jpg","width":480},"published":null,"summary":null,"updated":null,"upstreamDuplicates":null,"url":"http:\/\/29.media.tumblr.com\/tumblr_l8vijrvP0d1qanndio1_500.jpg","@download":"\/api\/ffffound\/download?url=http:\/\/img.ffffound.com\/static-data\/assets\/6\/c41872a4c5e91ad748f242816217ed7a121a6d87_m.jpg","@fffoundUrl":"http:\/\/ffffound.com\/image\/c41872a4c5e91ad748f242816217ed7a121a6d87"},"assetif405a9adedf99c2ce7d8103ee996663d8e58ca55":{"objectType":"file","fileUrl":null,"mimeType":null,"attachments":null,"author":null,"content":"The New Lomography Vienna Notebook: Add a Shot of Vienna to Your Daily Life! on Lomography","displayName":null,"downstreamDuplicates":null,"id":"assetif405a9adedf99c2ce7d8103ee996663d8e58ca55","image":{"duration":null,"height":463,"url":"http:\/\/img.ffffound.com\/static-data\/assets\/6\/f405a9adedf99c2ce7d8103ee996663d8e58ca55_m.jpg","width":480},"published":null,"summary":null,"updated":null,"upstreamDuplicates":null,"url":"http:\/\/www.lomography.com\/magazine\/blog\/2010\/02\/02\/the-new-lomography-vienna-notebook-add-a-shot-of-vienna-to-your-daily-life","@download":"\/api\/ffffound\/download?url=http:\/\/img.ffffound.com\/static-data\/assets\/6\/f405a9adedf99c2ce7d8103ee996663d8e58ca55_m.jpg","@fffoundUrl":"http:\/\/ffffound.com\/image\/f405a9adedf99c2ce7d8103ee996663d8e58ca55"},"asseti123514d247500f6b92b7120cd2af95e1115955e0":{"objectType":"file","fileUrl":null,"mimeType":null,"attachments":null,"author":null,"content":"M O O D","displayName":null,"downstreamDuplicates":null,"id":"asseti123514d247500f6b92b7120cd2af95e1115955e0","image":{"duration":null,"height":320,"url":"http:\/\/img.ffffound.com\/static-data\/assets\/6\/123514d247500f6b92b7120cd2af95e1115955e0_m.jpg","width":480},"published":null,"summary":null,"updated":null,"upstreamDuplicates":null,"url":"http:\/\/haw-lin.com\/","@download":"\/api\/ffffound\/download?url=http:\/\/img.ffffound.com\/static-data\/assets\/6\/123514d247500f6b92b7120cd2af95e1115955e0_m.jpg","@fffoundUrl":"http:\/\/ffffound.com\/image\/123514d247500f6b92b7120cd2af95e1115955e0"},"asseti622b7eb4f8e84f20a268c16bf8c91efe8db1e294":{"objectType":"file","fileUrl":null,"mimeType":null,"attachments":null,"author":null,"content":"\u2605 CJWHO","displayName":null,"downstreamDuplicates":null,"id":"asseti622b7eb4f8e84f20a268c16bf8c91efe8db1e294","image":{"duration":null,"height":384,"url":"http:\/\/img.ffffound.com\/static-data\/assets\/6\/622b7eb4f8e84f20a268c16bf8c91efe8db1e294_m.jpg","width":480},"published":null,"summary":null,"updated":null,"upstreamDuplicates":null,"url":"http:\/\/cjwho.tumblr.com\/","@download":"\/api\/ffffound\/download?url=http:\/\/img.ffffound.com\/static-data\/assets\/6\/622b7eb4f8e84f20a268c16bf8c91efe8db1e294_m.jpg","@fffoundUrl":"http:\/\/ffffound.com\/image\/622b7eb4f8e84f20a268c16bf8c91efe8db1e294"},"asseti40c3ce512e8f2649365f59be1f760a2fd574c7cc":{"objectType":"file","fileUrl":null,"mimeType":null,"attachments":null,"author":null,"content":"\u2605Baubauhaus.","displayName":null,"downstreamDuplicates":null,"id":"asseti40c3ce512e8f2649365f59be1f760a2fd574c7cc","image":{"duration":null,"height":480,"url":"http:\/\/img.ffffound.com\/static-data\/assets\/6\/40c3ce512e8f2649365f59be1f760a2fd574c7cc_m.jpg","width":322},"published":null,"summary":null,"updated":null,"upstreamDuplicates":null,"url":"http:\/\/baubauhaus.com\/post\/4099132720","@download":"\/api\/ffffound\/download?url=http:\/\/img.ffffound.com\/static-data\/assets\/6\/40c3ce512e8f2649365f59be1f760a2fd574c7cc_m.jpg","@fffoundUrl":"http:\/\/ffffound.com\/image\/40c3ce512e8f2649365f59be1f760a2fd574c7cc"},"asseti5b6e9b3a602daaeb6999db85c85517bb50cb1c4d":{"objectType":"file","fileUrl":null,"mimeType":null,"attachments":null,"author":null,"content":"Tumblr","displayName":null,"downstreamDuplicates":null,"id":"asseti5b6e9b3a602daaeb6999db85c85517bb50cb1c4d","image":{"duration":null,"height":321,"url":"http:\/\/img.ffffound.com\/static-data\/assets\/6\/5b6e9b3a602daaeb6999db85c85517bb50cb1c4d_m.jpg","width":480},"published":null,"summary":null,"updated":null,"upstreamDuplicates":null,"url":"http:\/\/www.tumblr.com\/dashboard\/213\/3217865360","@download":"\/api\/ffffound\/download?url=http:\/\/img.ffffound.com\/static-data\/assets\/6\/5b6e9b3a602daaeb6999db85c85517bb50cb1c4d_m.jpg","@fffoundUrl":"http:\/\/ffffound.com\/image\/5b6e9b3a602daaeb6999db85c85517bb50cb1c4d"},"asseti860a31780f43e1765a60bdda2faefbd70e1b8a7f":{"objectType":"file","fileUrl":null,"mimeType":null,"attachments":null,"author":null,"content":"\u30b5\u30a4","displayName":null,"downstreamDuplicates":null,"id":"asseti860a31780f43e1765a60bdda2faefbd70e1b8a7f","image":{"duration":null,"height":337,"url":"http:\/\/img.ffffound.com\/static-data\/assets\/6\/860a31780f43e1765a60bdda2faefbd70e1b8a7f_m.jpg","width":480},"published":null,"summary":null,"updated":null,"upstreamDuplicates":null,"url":"http:\/\/www.new-york-art.com\/Mus-Whitney-cy-twombly.htm","@download":"\/api\/ffffound\/download?url=http:\/\/img.ffffound.com\/static-data\/assets\/6\/860a31780f43e1765a60bdda2faefbd70e1b8a7f_m.jpg","@fffoundUrl":"http:\/\/ffffound.com\/image\/860a31780f43e1765a60bdda2faefbd70e1b8a7f"},"asseti52035e4b25c19697495162fe926923a6cc8610e9":{"objectType":"file","fileUrl":null,"mimeType":null,"attachments":null,"author":null,"content":"Time : OMG","displayName":null,"downstreamDuplicates":null,"id":"asseti52035e4b25c19697495162fe926923a6cc8610e9","image":{"duration":null,"height":373,"url":"http:\/\/img.ffffound.com\/static-data\/assets\/6\/52035e4b25c19697495162fe926923a6cc8610e9_m.jpg","width":480},"published":null,"summary":null,"updated":null,"upstreamDuplicates":null,"url":"http:\/\/olivermunday.com\/NEW\/index.php?\/illustration\/time\/","@download":"\/api\/ffffound\/download?url=http:\/\/img.ffffound.com\/static-data\/assets\/6\/52035e4b25c19697495162fe926923a6cc8610e9_m.jpg","@fffoundUrl":"http:\/\/ffffound.com\/image\/52035e4b25c19697495162fe926923a6cc8610e9"},"asseti9cd53f951f08841d90bfbc8caaaf3d370d20c497":{"objectType":"file","fileUrl":null,"mimeType":null,"attachments":null,"author":null,"content":"Nickel Cobalt","displayName":null,"downstreamDuplicates":null,"id":"asseti9cd53f951f08841d90bfbc8caaaf3d370d20c497","image":{"duration":null,"height":480,"url":"http:\/\/img.ffffound.com\/static-data\/assets\/6\/9cd53f951f08841d90bfbc8caaaf3d370d20c497_m.jpg","width":343},"published":null,"summary":null,"updated":null,"upstreamDuplicates":null,"url":"http:\/\/nickelcobalt.tumblr.com\/page\/2","@download":"\/api\/ffffound\/download?url=http:\/\/img.ffffound.com\/static-data\/assets\/6\/9cd53f951f08841d90bfbc8caaaf3d370d20c497_m.jpg","@fffoundUrl":"http:\/\/ffffound.com\/image\/9cd53f951f08841d90bfbc8caaaf3d370d20c497"},"assetib31685bb629109e2c1e19faeb7365ab14203cd4e":{"objectType":"file","fileUrl":null,"mimeType":null,"attachments":null,"author":null,"content":"Jessica Hische","displayName":null,"downstreamDuplicates":null,"id":"assetib31685bb629109e2c1e19faeb7365ab14203cd4e","image":{"duration":null,"height":400,"url":"http:\/\/img.ffffound.com\/static-data\/assets\/6\/b31685bb629109e2c1e19faeb7365ab14203cd4e_m.png","width":480},"published":null,"summary":null,"updated":null,"upstreamDuplicates":null,"url":"http:\/\/jessicahische.com\/designifies\/a-logo-for-a-lovely-interior-designer","@download":"\/api\/ffffound\/download?url=http:\/\/img.ffffound.com\/static-data\/assets\/6\/b31685bb629109e2c1e19faeb7365ab14203cd4e_m.png","@fffoundUrl":"http:\/\/ffffound.com\/image\/b31685bb629109e2c1e19faeb7365ab14203cd4e"},"assetia55419702e0f8fd543987d47266a7a38c36396b6":{"objectType":"file","fileUrl":null,"mimeType":null,"attachments":null,"author":null,"content":"void()","displayName":null,"downstreamDuplicates":null,"id":"assetia55419702e0f8fd543987d47266a7a38c36396b6","image":{"duration":null,"height":353,"url":"http:\/\/img.ffffound.com\/static-data\/assets\/6\/a55419702e0f8fd543987d47266a7a38c36396b6_m.jpg","width":480},"published":null,"summary":null,"updated":null,"upstreamDuplicates":null,"url":"http:\/\/www.qubik.com\/zr\/","@download":"\/api\/ffffound\/download?url=http:\/\/img.ffffound.com\/static-data\/assets\/6\/a55419702e0f8fd543987d47266a7a38c36396b6_m.jpg","@fffoundUrl":"http:\/\/ffffound.com\/image\/a55419702e0f8fd543987d47266a7a38c36396b6"},"asseti298c6e7c39b195cfca6649aacc102b33cff913bc":{"objectType":"file","fileUrl":null,"mimeType":null,"attachments":null,"author":null,"content":"Tumblr","displayName":null,"downstreamDuplicates":null,"id":"asseti298c6e7c39b195cfca6649aacc102b33cff913bc","image":{"duration":null,"height":330,"url":"http:\/\/img.ffffound.com\/static-data\/assets\/6\/298c6e7c39b195cfca6649aacc102b33cff913bc_m.jpg","width":480},"published":null,"summary":null,"updated":null,"upstreamDuplicates":null,"url":"http:\/\/www.tumblr.com\/dashboard\/34\/1572844678","@download":"\/api\/ffffound\/download?url=http:\/\/img.ffffound.com\/static-data\/assets\/6\/298c6e7c39b195cfca6649aacc102b33cff913bc_m.jpg","@fffoundUrl":"http:\/\/ffffound.com\/image\/298c6e7c39b195cfca6649aacc102b33cff913bc"},"asseti2f7f95282ca29417ceaac6ee3bb4e52dc345b32c":{"objectType":"file","fileUrl":null,"mimeType":null,"attachments":null,"author":null,"content":"supersonic electronic","displayName":null,"downstreamDuplicates":null,"id":"asseti2f7f95282ca29417ceaac6ee3bb4e52dc345b32c","image":{"duration":null,"height":467,"url":"http:\/\/img.ffffound.com\/static-data\/assets\/6\/2f7f95282ca29417ceaac6ee3bb4e52dc345b32c_m.jpg","width":480},"published":null,"summary":null,"updated":null,"upstreamDuplicates":null,"url":"http:\/\/supersonicelectronic.com\/","@download":"\/api\/ffffound\/download?url=http:\/\/img.ffffound.com\/static-data\/assets\/6\/2f7f95282ca29417ceaac6ee3bb4e52dc345b32c_m.jpg","@fffoundUrl":"http:\/\/ffffound.com\/image\/2f7f95282ca29417ceaac6ee3bb4e52dc345b32c"}}